odoo8_addon_shopinvader_paypal-8.0.1.0.0.99.dev10-py3.8-nspkg.pth
odoo_addons/shopinvader_paypal/README.rst
odoo_addons/shopinvader_paypal/__init__.py
odoo_addons/shopinvader_paypal/__openerp__.py
odoo_addons/shopinvader_paypal/demo/shopinvader_payment_demo.xml
odoo_addons/shopinvader_paypal/services/__init__.py
odoo_addons/shopinvader_paypal/services/payment_service.py
odoo_addons/shopinvader_paypal/tests/__init__.py
odoo_addons/shopinvader_paypal/tests/test_payment.py
odoo8_addon_shopinvader_paypal-8.0.1.0.0.99.dev10.dist-info/METADATA
odoo8_addon_shopinvader_paypal-8.0.1.0.0.99.dev10.dist-info/WHEEL
odoo8_addon_shopinvader_paypal-8.0.1.0.0.99.dev10.dist-info/namespace_packages.txt
odoo8_addon_shopinvader_paypal-8.0.1.0.0.99.dev10.dist-info/top_level.txt
odoo8_addon_shopinvader_paypal-8.0.1.0.0.99.dev10.dist-info/RECORD
